{
  "backupId": "20260719T160000Z",
  "credentialMutation": false,
  "daemonReloaded": false,
  "decisionDigest": "sha256:4444444444444444444444444444444444444444444444444444444444444444",
  "dependencySourceCount": 5,
  "gatewayPid": 100,
  "gatewayProcessUnchanged": true,
  "httpImporterRollbackSnapshotRetained": true,
  "liveProcessReferences": 0,
  "phiServiceRestarted": false,
  "quarantineRetained": true,
  "recoveryScriptPrepared": true,
  "referenceUnitCount": 3,
  "releaseActivated": false,
  "releaseVersion": "0.1.21",
  "runtimeDeleted": false,
  "runtimeLive": false,
  "scheduledReferences": 0,
  "schema": "cloudx.cloud-legacy-runtime-quarantine.v1",
  "selectorsUnchanged": true,
  "serviceRestarted": false,
  "status": "quarantined",
  "targetBytes": 4096,
  "targetFileCount": 2,
  "targetTreeSha256": "5555555555555555555555555555555555555555555555555555555555555555"
}
